pyerc20/__init__.py
pyerc20/erc20/__init__.py
pyerc20/erc20/_abi.py
pyerc20/erc20/erc20.py
pyerc20/weth/__init__.py
pyerc20/weth/_abi.py
pyerc20/weth/weth.py
pyerc20-0.1.1.dist-info/METADATA
pyerc20-0.1.1.dist-info/WHEEL
pyerc20-0.1.1.dist-info/RECORD
